{
    "expense": {
        "basics" : {
            "title": "Basics",
            "img": "./assets/icons/groceries.png",
            "subItems" : {
                "0":{
                    "title": "Food & Drinks",                    
                    "img": "./assets/icons/food.png"
                },
                "1":{
                    "title": "Bill",                    
                    "img": "./assets/icons/bill.png"
                },
                "2":{
                    "title": "Transport",                    
                    "img": "./assets/icons/transport.png"
                },
                "3":{
                    "title": "House Rent",                    
                    "img": "./assets/icons/house-rent.png"
                },
                "4":{
                    "title": "Fix & Maintenance",                    
                    "img": "./assets/icons/maintenance.png"
                },
                "5":{
                    "title": "Utilities",                    
                    "img": "./assets/icons/utilities.png"
                },
                "6":{
                    "title": "Groceries",                    
                    "img": "./assets/icons/groceries.png"
                }
            }
        },
        "enjoyment" : {
            "title": "Enjoyment",
            "img": "./assets/icons/party.png",
            "subItems" : {
                "0": {
                    "title": "Entertainment",                    
                    "img": "./assets/icons/entertainment.png"
                },
                "1": {
                    "title": "Fashion",                    
                    "img": "./assets/icons/fashion.png"
                },
                "2": {
                    "title": "Travel",                    
                    "img": "./assets/icons/travel.png"
                },
                "3": {
                    "title": "Beauty Care",                    
                    "img": "./assets/icons/beauty-care.png"
                },
                "4": {
                    "title": "Party",                    
                    "img": "./assets/icons/party.png"
                }
            }
        },
        "HealthCare" : {
            "title": "HealthCare",
            "img": "./assets/icons/health-care.png",
            "subItems" : {
                "0": {
                    "title": "Doctor",                    
                    "img": "./assets/icons/doctor.png"
                },
                "1": {
                    "title": "Sport",                    
                    "img": "./assets/icons/sport.png"
                },
                "2": {
                    "title": "Insurance",                    
                    "img": "./assets/icons/insurance.png"
                }
            }
        },
        "Give" : {
            "title": "Give",
            "img": "./assets/icons/party.png",
            "subItems" : {
                "0": {
                    "title": "Gift",                    
                    "img": "./assets/icons/gift.png"
                }
            }
        }
    },
    "incomes": {
        "salary" : {
            "title": "Salary",
            "img": "./assets/icons/salary.png"
        },
        "award" : {
            "title": "Award",
            "img": "./assets/icons/award.png"
        },
        "otherIncoms" : {
            "title": "Other Incoms",
            "img": "./assets/icons/other-income.png"
        }
    },
    "debts": {
        "lend" : {
            "title": "Lend",
            "img": "./assets/icons/lend.png"
        },
        "borrow" : {
            "title": "Borrow",
            "img": "./assets/icons/borrow.png"
        }
    }
}